{
  "buffers": [
    {
      "alignment": 4,
      "batch": 0,
      "channel_first": true,
      "channel_last": true,
      "epochs": {
        "end": 1,
        "start": 0
      },
      "flags": "STAI_FLAG_WEIGHTS|STAI_FLAG_CONST|STAI_FLAG_PREALLOCATED",
      "format": "STAI_FORMAT_S32",
      "id": 195,
      "intq": {
        "axis": null,
        "offsets": [],
        "scales": []
      },
      "is_param": true,
      "mpool_id": 1,
      "name": "conv2d_1_bias_array",
      "nbits": 32,
      "offset_start": 144,
      "qmn": {},
      "shape": [
        16
      ],
      "shape_map": [
        "CH"
      ],
      "size_bytes": 64
    },
    {
      "alignment": 4,
      "batch": 0,
      "channel_first": false,
      "channel_last": true,
      "epochs": {
        "end": 12,
        "start": 6
      },
      "flags": "STAI_FLAG_PREALLOCATED|STAI_FLAG_ACTIVATIONS",
      "format": "STAI_FORMAT_S8",
      "id": 174,
      "intq": {
        "axis": 2,
        "offsets": [
          -128
        ],
        "scales": [
          64.04903411865234
        ]
      },
      "is_param": false,
      "mpool_id": 0,
      "name": "conv2d_1_output_array",
      "nbits": 8,
      "offset_start": 448,
      "qmn": {},
      "shape": [
        30,
        30,
        16
      ],
      "shape_map": [
        "H",
        "W",
        "CH"
      ],
      "size_bytes": 14400
    },
    {
      "alignment": 4,
      "batch": 0,
      "channel_first": false,
      "channel_last": true,
      "epochs": {
        "end": 8,
        "start": 5
      },
      "flags": "STAI_FLAG_PREALLOCATED|STAI_FLAG_ACTIVATIONS|STAI_FLAG_SCRATCHS",
      "format": "STAI_FORMAT_S8",
      "id": 237,
      "intq": {
        "axis": null,
        "offsets": [],
        "scales": []
      },
      "is_param": false,
      "mpool_id": 0,
      "name": "conv2d_1_scratch0_array",
      "nbits": 8,
      "offset_start": 14848,
      "qmn": {},
      "shape": [
        1,
        1,
        548,
        1
      ],
      "shape_map": [
        "H",
        "W",
        "CH",
        "CH_IN"
      ],
      "size_bytes": 548
    },
    {
      "alignment": 4,
      "batch": 0,
      "channel_first": true,
      "channel_last": false,
      "epochs": {
        "end": 1,
        "start": 0
      },
      "flags": "STAI_FLAG_WEIGHTS|STAI_FLAG_CONST|STAI_FLAG_PREALLOCATED",
      "format": "STAI_FORMAT_S8",
      "id": 192,
      "intq": {
        "axis": 3,
        "offsets": [
          0,
          0,
          0,
          0,
          0,
          0,
          0,
          0,
          0,
          0,
          0,
          0,
          0,
          0,
          0,
          0
        ],
        "scales": [
          0.001988318283110857,
          0.001123588066548109,
          0.0019371163798496127,
          0.001929433667100966,
          0.0019192270701751113,
          0.001801675301976502,
          0.0016273154178634286,
          0.002164730103686452,
          0.0018706141272559762,
          0.00187613011803478,
          0.0020057379733771086,
          0.0019041409250348806,
          0.001939401845447719,
          0.002021356485784054,
          0.0017763637006282806,
          0.001196294673718512
        ]
      },
      "is_param": true,
      "mpool_id": 1,
      "name": "conv2d_1_weights_array",
      "nbits": 8,
      "offset_start": 0,
      "qmn": {},
      "shape": [
        16,
        3,
        3,
        1
      ],
      "shape_map": [
        "CH",
        "H",
        "W",
        "CH_IN"
      ],
      "size_bytes": 144
    },
    {
      "alignment": 4,
      "batch": 0,
      "channel_first": true,
      "channel_last": true,
      "epochs": {
        "end": 1,
        "start": 0
      },
      "flags": "STAI_FLAG_WEIGHTS|STAI_FLAG_CONST|STAI_FLAG_PREALLOCATED",
      "format": "STAI_FORMAT_S32",
      "id": 201,
      "intq": {
        "axis": null,
        "offsets": [],
        "scales": []
      },
      "is_param": true,
      "mpool_id": 1,
      "name": "conv2d_2_bias_array",
      "nbits": 32,
      "offset_start": 4816,
      "qmn": {},
      "shape": [
        32
      ],
      "shape_map": [
        "CH"
      ],
      "size_bytes": 128
    },
    {
      "alignment": 4,
      "batch": 0,
      "channel_first": false,
      "channel_last": true,
      "epochs": {
        "end": 17,
        "start": 11
      },
      "flags": "STAI_FLAG_PREALLOCATED|STAI_FLAG_ACTIVATIONS",
      "format": "STAI_FORMAT_S8",
      "id": 176,
      "intq": {
        "axis": 2,
        "offsets": [
          -128
        ],
        "scales": [
          93.70098876953125
        ]
      },
      "is_param": false,
      "mpool_id": 0,
      "name": "conv2d_2_output_array",
      "nbits": 8,
      "offset_start": 0,
      "qmn": {},
      "shape": [
        14,
        14,
        32
      ],
      "shape_map": [
        "H",
        "W",
        "CH"
      ],
      "size_bytes": 6272
    },
    {
      "alignment": 4,
      "batch": 0,
      "channel_first": false,
      "channel_last": true,
      "epochs": {
        "end": 13,
        "start": 9
      },
      "flags": "STAI_FLAG_PREALLOCATED|STAI_FLAG_ACTIVATIONS|STAI_FLAG_SCRATCHS",
      "format": "STAI_FORMAT_S8",
      "id": 246,
      "intq": {
        "axis": null,
        "offsets": [],
        "scales": []
      },
      "is_param": false,
      "mpool_id": 0,
      "name": "conv2d_2_scratch0_array",
      "nbits": 8,
      "offset_start": 14848,
      "qmn": {},
      "shape": [
        1,
        1,
        6144,
        1
      ],
      "shape_map": [
        "H",
        "W",
        "CH",
        "CH_IN"
      ],
      "size_bytes": 6144
    },
    {
      "alignment": 4,
      "batch": 0,
      "channel_first": false,
      "channel_last": true,
      "epochs": {
        "end": 14,
        "start": 10
      },
      "flags": "STAI_FLAG_PREALLOCATED|STAI_FLAG_ACTIVATIONS|STAI_FLAG_SCRATCHS",
      "format": "STAI_FORMAT_S8",
      "id": 250,
      "intq": {
        "axis": 3,
        "offsets": [
          -128
        ],
        "scales": [
          93.70098876953125
        ]
      },
      "is_param": false,
      "mpool_id": 0,
      "name": "conv2d_2_scratch1_array",
      "nbits": 8,
      "offset_start": 20992,
      "qmn": {},
      "shape": [
        2,
        28,
        32,
        1
      ],
      "shape_map": [
        "H",
        "W",
        "CH",
        "CH_IN"
      ],
      "size_bytes": 1792
    },
    {
      "alignment": 4,
      "batch": 0,
      "channel_first": true,
      "channel_last": false,
      "epochs": {
        "end": 1,
        "start": 0
      },
      "flags": "STAI_FLAG_WEIGHTS|STAI_FLAG_CONST|STAI_FLAG_PREALLOCATED",
      "format": "STAI_FORMAT_S8",
      "id": 198,
      "intq": {
        "axis": 3,
        "offsets": [
          0,
          0,
          0,
          0,
          0,
          0,
          0,
          0,
          0,
          0,
          0,
          0,
          0,
          0,
          0,
          0,
          0,
          0,
          0,
          0,
          0,
          0,
          0,
          0,
          0,
          0,
          0,
          0,
          0,
          0,
          0,
          0
        ],
        "scales": [
          0.001335797249339521,
          0.0013249203329905868,
          0.0016007196391001344,
          0.0012829946354031563,
          0.0016290538478642702,
          0.0015611648559570312,
          0.0013773570535704494,
          0.0012791401240974665,
          0.0012603740906342864,
          0.001250941539183259,
          0.0016243037534877658,
          0.0016133141471073031,
          0.0012008837657049298,
          0.0016283493023365736,
          0.0015844962326809764,
          0.0013485255185514688,
          0.0018678036285564303,
          0.0012868148041889071,
          0.0013582701794803143,
          0.0013491595163941383,
          0.0014301418559625745,
          0.0013425123179331422,
          0.0014874555636197329,
          0.0012320680543780327,
          0.001243367325514555,
          0.001777303172275424,
          0.0012596636079251766,
          0.0013008264359086752,
          0.0012312486069276929,
          0.0012447801418602467,
          0.0015691487351432443,
          0.0012327589793130755
        ]
      },
      "is_param": true,
      "mpool_id": 1,
      "name": "conv2d_2_weights_array",
      "nbits": 8,
      "offset_start": 208,
      "qmn": {},
      "shape": [
        32,
        3,
        3,
        16
      ],
      "shape_map": [
        "CH",
        "H",
        "W",
        "CH_IN"
      ],
      "size_bytes": 4608
    },
    {
      "alignment": 4,
      "batch": 0,
      "channel_first": true,
      "channel_last": true,
      "epochs": {
        "end": 1,
        "start": 0
      },
      "flags": "STAI_FLAG_WEIGHTS|STAI_FLAG_CONST|STAI_FLAG_PREALLOCATED",
      "format": "STAI_FORMAT_S32",
      "id": 207,
      "intq": {
        "axis": null,
        "offsets": [],
        "scales": []
      },
      "is_param": true,
      "mpool_id": 1,
      "name": "conv2d_4_bias_array",
      "nbits": 32,
      "offset_start": 14160,
      "qmn": {},
      "shape": [
        32
      ],
      "shape_map": [
        "CH"
      ],
      "size_bytes": 128
    },
    {
      "alignment": 4,
      "batch": 0,
      "channel_first": false,
      "channel_last": true,
      "epochs": {
        "end": 21,
        "start": 16
      },
      "flags": "STAI_FLAG_PREALLOCATED|STAI_FLAG_ACTIVATIONS",
      "format": "STAI_FORMAT_S8",
      "id": 178,
      "intq": {
        "axis": 2,
        "offsets": [
          -128
        ],
        "scales": [
          145.46844482421875
        ]
      },
      "is_param": false,
      "mpool_id": 0,
      "name": "conv2d_4_output_array",
      "nbits": 8,
      "offset_start": 18176,
      "qmn": {},
      "shape": [
        12,
        12,
        32
      ],
      "shape_map": [
        "H",
        "W",
        "CH"
      ],
      "size_bytes": 4608
    },
    {
      "alignment": 4,
      "batch": 0,
      "channel_first": false,
      "channel_last": true,
      "epochs": {
        "end": 18,
        "start": 15
      },
      "flags": "STAI_FLAG_PREALLOCATED|STAI_FLAG_ACTIVATIONS|STAI_FLAG_SCRATCHS",
      "format": "STAI_FORMAT_S8",
      "id": 256,
      "intq": {
        "axis": null,
        "offsets": [],
        "scales": []
      },
      "is_param": false,
      "mpool_id": 0,
      "name": "conv2d_4_scratch0_array",
      "nbits": 8,
      "offset_start": 6272,
      "qmn": {},
      "shape": [
        1,
        1,
        6720,
        1
      ],
      "shape_map": [
        "H",
        "W",
        "CH",
        "CH_IN"
      ],
      "size_bytes": 6720
    },
    {
      "alignment": 4,
      "batch": 0,
      "channel_first": true,
      "channel_last": false,
      "epochs": {
        "end": 1,
        "start": 0
      },
      "flags": "STAI_FLAG_WEIGHTS|STAI_FLAG_CONST|STAI_FLAG_PREALLOCATED",
      "format": "STAI_FORMAT_S8",
      "id": 204,
      "intq": {
        "axis": 3,
        "offsets": [
          0,
          0,
          0,
          0,
          0,
          0,
          0,
          0,
          0,
          0,
          0,
          0,
          0,
          0,
          0,
          0,
          0,
          0,
          0,
          0,
          0,
          0,
          0,
          0,
          0,
          0,
          0,
          0,
          0,
          0,
          0,
          0
        ],
        "scales": [
          0.0014575981767848134,
          0.0015284748515114188,
          0.0013170206220820546,
          0.00101719971280545,
          0.0013562985695898533,
          0.001347587676718831,
          0.0013730587670579553,
          0.0010468156542629004,
          0.0013092992594465613,
          0.0013513704761862755,
          0.0012765397550538182,
          0.0011673405533656478,
          0.0014015320921316743,
          0.0010639664251357317,
          0.0013891394482925534,
          0.0012064147740602493,
          0.0011839654762297869,
          0.0015841919230297208,
          0.001235986826941371,
          0.0012707929126918316,
          0.001433591009117663,
          0.0013813445111736655,
          0.0011918789241462946,
          0.0014221161836758256,
          0.0012580821057781577,
          0.001363971852697432,
          0.001443939283490181,
          0.0015920583391562104,
          0.0012155293952673674,
          0.0013316302793100476,
          0.0013320940779522061,
          0.0011894123163074255
        ]
      },
      "is_param": true,
      "mpool_id": 1,
      "name": "conv2d_4_weights_array",
      "nbits": 8,
      "offset_start": 4944,
      "qmn": {},
      "shape": [
        32,
        3,
        3,
        32
      ],
      "shape_map": [
        "CH",
        "H",
        "W",
        "CH_IN"
      ],
      "size_bytes": 9216
    },
    {
      "alignment": 4,
      "batch": 0,
      "channel_first": true,
      "channel_last": true,
      "epochs": {
        "end": 1,
        "start": 0
      },
      "flags": "STAI_FLAG_WEIGHTS|STAI_FLAG_CONST|STAI_FLAG_PREALLOCATED",
      "format": "STAI_FORMAT_S32",
      "id": 213,
      "intq": {
        "axis": null,
        "offsets": [],
        "scales": []
      },
      "is_param": true,
      "mpool_id": 1,
      "name": "conv2d_5_bias_array",
      "nbits": 32,
      "offset_start": 32720,
      "qmn": {},
      "shape": [
        64
      ],
      "shape_map": [
        "CH"
      ],
      "size_bytes": 256
    },
    {
      "alignment": 4,
      "batch": 0,
      "channel_first": false,
      "channel_last": true,
      "epochs": {
        "end": 25,
        "start": 20
      },
      "flags": "STAI_FLAG_PREALLOCATED|STAI_FLAG_ACTIVATIONS",
      "format": "STAI_FORMAT_S8",
      "id": 180,
      "intq": {
        "axis": 2,
        "offsets": [
          -128
        ],
        "scales": [
          102.85371398925781
        ]
      },
      "is_param": false,
      "mpool_id": 0,
      "name": "conv2d_5_output_array",
      "nbits": 8,
      "offset_start": 14976,
      "qmn": {},
      "shape": [
        10,
        10,
        64
      ],
      "shape_map": [
        "H",
        "W",
        "CH"
      ],
      "size_bytes": 6400
    },
    {
      "alignment": 4,
      "batch": 0,
      "channel_first": false,
      "channel_last": true,
      "epochs": {
        "end": 22,
        "start": 19
      },
      "flags": "STAI_FLAG_PREALLOCATED|STAI_FLAG_ACTIVATIONS|STAI_FLAG_SCRATCHS",
      "format": "STAI_FORMAT_S8",
      "id": 262,
      "intq": {
        "axis": null,
        "offsets": [],
        "scales": []
      },
      "is_param": false,
      "mpool_id": 0,
      "name": "conv2d_5_scratch0_array",
      "nbits": 8,
      "offset_start": 0,
      "qmn": {},
      "shape": [
        1,
        1,
        7168,
        1
      ],
      "shape_map": [
        "H",
        "W",
        "CH",
        "CH_IN"
      ],
      "size_bytes": 7168
    },
    {
      "alignment": 4,
      "batch": 0,
      "channel_first": true,
      "channel_last": false,
      "epochs": {
        "end": 1,
        "start": 0
      },
      "flags": "STAI_FLAG_WEIGHTS|STAI_FLAG_CONST|STAI_FLAG_PREALLOCATED",
      "format": "STAI_FORMAT_S8",
      "id": 210,
      "intq": {
        "axis": 3,
        "offsets": [
          0,
          0,
          0,
          0,
          0,
          0,
          0,
          0,
          0,
          0,
          0,
          0,
          0,
          0,
          0,
          0,
          0,
          0,
          0,
          0,
          0,
          0,
          0,
          0,
          0,
          0,
          0,
          0,
          0,
          0,
          0,
          0,
          0,
          0,
          0,
          0,
          0,
          0,
          0,
          0,
          0,
          0,
          0,
          0,
          0,
          0,
          0,
          0,
          0,
          0,
          0,
          0,
          0,
          0,
          0,
          0,
          0,
          0,
          0,
          0,
          0,
          0,
          0,
          0
        ],
        "scales": [
          0.0012607583776116371,
          0.0013097672490403056,
          0.0012226431863382459,
          0.0013273805379867554,
          0.0011488914024084806,
          0.001003884943202138,
          0.001421644352376461,
          0.001005446189083159,
          0.001135039608925581,
          0.0010031944839283824,
          0.0011270847171545029,
          0.0009637554176151752,
          0.0011479343520477414,
          0.001042171847075224,
          0.0010451368289068341,
          0.0009565785876475275,
          0.0010137991048395634,
          0.001064496231265366,
          0.0010462342761456966,
          0.0009305297862738371,
          0.0010750711662694812,
          0.0008816357585601509,
          0.0012247650884091854,
          0.0009836623212322593,
          0.0009585447260178626,
          0.0008506915764883161,
          0.0011063828133046627,
          0.0008257223526015878,
          0.0010108554270118475,
          0.0011123325675725937,
          0.0012353940401226282,
          0.001053332700394094,
          0.0009629674605093896,
          0.0010518237249925733,
          0.0011366762919351459,
          0.0010578541550785303,
          0.0009250336443074048,
          0.0009842501021921635,
          0.001104112365283072,
          0.0010153563925996423,
          0.0009213140001520514,
          0.0009654554887674749,
          0.0011536419624462724,
          0.0011245835339650512,
          0.0009634363814257085,
          0.0010066760005429387,
          0.0011090844636783004,
          0.0009622426587156951,
          0.00088907202007249,
          0.0011342719662934542,
          0.0012271805899217725,
          0.0011593047529459,
          0.0011724128853529692,
          0.0012754126219078898,
          0.0010222871787846088,
          0.000991813256405294,
          0.0008746552630327642,
          0.001272788387723267,
          0.0011719476897269487,
          0.001002715085633099,
          0.0009722030954435468,
          0.0009355738293379545,
          0.0010655669029802084,
          0.0012142328778281808
        ]
      },
      "is_param": true,
      "mpool_id": 1,
      "name": "conv2d_5_weights_array",
      "nbits": 8,
      "offset_start": 14288,
      "qmn": {},
      "shape": [
        64,
        3,
        3,
        32
      ],
      "shape_map": [
        "CH",
        "H",
        "W",
        "CH_IN"
      ],
      "size_bytes": 18432
    },
    {
      "alignment": 4,
      "batch": 0,
      "channel_first": false,
      "channel_last": true,
      "epochs": {
        "end": 7,
        "start": 3
      },
      "flags": "STAI_FLAG_PREALLOCATED|STAI_FLAG_ACTIVATIONS",
      "format": "STAI_FORMAT_S8",
      "id": 172,
      "intq": {
        "axis": 2,
        "offsets": [
          -128
        ],
        "scales": [
          118.0536117553711
        ]
      },
      "is_param": false,
      "mpool_id": 0,
      "name": "conversion_0_output_array",
      "nbits": 8,
      "offset_start": 15396,
      "qmn": {},
      "shape": [
        32,
        32,
        1
      ],
      "shape_map": [
        "H",
        "W",
        "CH"
      ],
      "size_bytes": 1024
    },
    {
      "alignment": 4,
      "batch": 0,
      "channel_first": true,
      "channel_last": true,
      "epochs": {
        "end": 41,
        "start": 39
      },
      "flags": "STAI_FLAG_OUTPUTS|STAI_FLAG_PREALLOCATED|STAI_FLAG_ACTIVATIONS",
      "format": "STAI_FORMAT_FLOAT",
      "id": 190,
      "intq": {
        "axis": null,
        "offsets": [],
        "scales": []
      },
      "is_param": false,
      "mpool_id": 0,
      "name": "conversion_11_output_array",
      "nbits": 32,
      "offset_start": 8,
      "qmn": {},
      "shape": [
        4
      ],
      "shape_map": [
        "CH"
      ],
      "size_bytes": 16
    },
    {
      "alignment": 4,
      "batch": 0,
      "channel_first": true,
      "channel_last": true,
      "epochs": {
        "end": 1,
        "start": 0
      },
      "flags": "STAI_FLAG_WEIGHTS|STAI_FLAG_CONST|STAI_FLAG_PREALLOCATED",
      "format": "STAI_FORMAT_S32",
      "id": 219,
      "intq": {
        "axis": null,
        "offsets": [],
        "scales": []
      },
      "is_param": true,
      "mpool_id": 1,
      "name": "gemm_7_bias_array",
      "nbits": 32,
      "offset_start": 135376,
      "qmn": {},
      "shape": [
        16
      ],
      "shape_map": [
        "CH"
      ],
      "size_bytes": 64
    },
    {
      "alignment": 4,
      "batch": 0,
      "channel_first": true,
      "channel_last": true,
      "epochs": {
        "end": 29,
        "start": 24
      },
      "flags": "STAI_FLAG_PREALLOCATED|STAI_FLAG_ACTIVATIONS",
      "format": "STAI_FORMAT_S8",
      "id": 182,
      "intq": {
        "axis": 0,
        "offsets": [
          -128
        ],
        "scales": [
          183.6317901611328
        ]
      },
      "is_param": false,
      "mpool_id": 0,
      "name": "gemm_7_output_array",
      "nbits": 8,
      "offset_start": 12960,
      "qmn": {},
      "shape": [
        16
      ],
      "shape_map": [
        "CH"
      ],
      "size_bytes": 16
    },
    {
      "alignment": 4,
      "batch": 0,
      "channel_first": false,
      "channel_last": true,
      "epochs": {
        "end": 26,
        "start": 23
      },
      "flags": "STAI_FLAG_PREALLOCATED|STAI_FLAG_ACTIVATIONS|STAI_FLAG_SCRATCHS",
      "format": "STAI_FORMAT_S16",
      "id": 268,
      "intq": {
        "axis": null,
        "offsets": [],
        "scales": []
      },
      "is_param": false,
      "mpool_id": 0,
      "name": "gemm_7_scratch0_array",
      "nbits": 16,
      "offset_start": 0,
      "qmn": {},
      "shape": [
        1,
        1,
        6480,
        1
      ],
      "shape_map": [
        "H",
        "W",
        "CH",
        "CH_IN"
      ],
      "size_bytes": 12960
    },
    {
      "alignment": 4,
      "batch": 0,
      "channel_first": true,
      "channel_last": true,
      "epochs": {
        "end": 1,
        "start": 0
      },
      "flags": "STAI_FLAG_WEIGHTS|STAI_FLAG_CONST|STAI_FLAG_PREALLOCATED",
      "format": "STAI_FORMAT_S8",
      "id": 216,
      "intq": {
        "axis": 1,
        "offsets": [
          0,
          0,
          0,
          0,
          0,
          0,
          0,
          0,
          0,
          0,
          0,
          0,
          0,
          0,
          0,
          0
        ],
        "scales": [
          0.00028680753894150257,
          0.0009916058043017983,
          0.0010040609631687403,
          0.0009712442406453192,
          0.0008558132103644311,
          0.0008927288581617177,
          0.0009388518519699574,
          0.0007919779745861888,
          0.0007384600467048585,
          0.0008903456036932766,
          0.0006908854120410979,
          0.000848804076667875,
          0.0008623625035397708,
          0.0010109671857208014,
          0.0011015902273356915,
          0.0008636947604827583
        ]
      },
      "is_param": true,
      "mpool_id": 1,
      "name": "gemm_7_weights_array",
      "nbits": 8,
      "offset_start": 32976,
      "qmn": {},
      "shape": [
        16,
        6400
      ],
      "shape_map": [
        "CH",
        "CH_IN"
      ],
      "size_bytes": 102400
    },
    {
      "alignment": 4,
      "batch": 0,
      "channel_first": true,
      "channel_last": true,
      "epochs": {
        "end": 1,
        "start": 0
      },
      "flags": "STAI_FLAG_WEIGHTS|STAI_FLAG_CONST|STAI_FLAG_PREALLOCATED",
      "format": "STAI_FORMAT_S32",
      "id": 225,
      "intq": {
        "axis": null,
        "offsets": [],
        "scales": []
      },
      "is_param": true,
      "mpool_id": 1,
      "name": "gemm_8_bias_array",
      "nbits": 32,
      "offset_start": 137488,
      "qmn": {},
      "shape": [
        128
      ],
      "shape_map": [
        "CH"
      ],
      "size_bytes": 512
    },
    {
      "alignment": 4,
      "batch": 0,
      "channel_first": true,
      "channel_last": true,
      "epochs": {
        "end": 33,
        "start": 28
      },
      "flags": "STAI_FLAG_PREALLOCATED|STAI_FLAG_ACTIVATIONS",
      "format": "STAI_FORMAT_S8",
      "id": 184,
      "intq": {
        "axis": 0,
        "offsets": [
          -128
        ],
        "scales": [
          88.4465103149414
        ]
      },
      "is_param": false,
      "mpool_id": 0,
      "name": "gemm_8_output_array",
      "nbits": 8,
      "offset_start": 1312,
      "qmn": {},
      "shape": [
        128
      ],
      "shape_map": [
        "CH"
      ],
      "size_bytes": 128
    },
    {
      "alignment": 4,
      "batch": 0,
      "channel_first": false,
      "channel_last": true,
      "epochs": {
        "end": 30,
        "start": 27
      },
      "flags": "STAI_FLAG_PREALLOCATED|STAI_FLAG_ACTIVATIONS|STAI_FLAG_SCRATCHS",
      "format": "STAI_FORMAT_S16",
      "id": 274,
      "intq": {
        "axis": null,
        "offsets": [],
        "scales": []
      },
      "is_param": false,
      "mpool_id": 0,
      "name": "gemm_8_scratch0_array",
      "nbits": 16,
      "offset_start": 0,
      "qmn": {},
      "shape": [
        1,
        1,
        656,
        1
      ],
      "shape_map": [
        "H",
        "W",
        "CH",
        "CH_IN"
      ],
      "size_bytes": 1312
    },
    {
      "alignment": 4,
      "batch": 0,
      "channel_first": true,
      "channel_last": true,
      "epochs": {
        "end": 1,
        "start": 0
      },
      "flags": "STAI_FLAG_WEIGHTS|STAI_FLAG_CONST|STAI_FLAG_PREALLOCATED",
      "format": "STAI_FORMAT_S8",
      "id": 222,
      "intq": {
        "axis": 1,
        "offsets": [
          0,
          0,
          0,
          0,
          0,
          0,
          0,
          0,
          0,
          0,
          0,
          0,
          0,
          0,
          0,
          0,
          0,
          0,
          0,
          0,
          0,
          0,
          0,
          0,
          0,
          0,
          0,
          0,
          0,
          0,
          0,
          0,
          0,
          0,
          0,
          0,
          0,
          0,
          0,
          0,
          0,
          0,
          0,
          0,
          0,
          0,
          0,
          0,
          0,
          0,
          0,
          0,
          0,
          0,
          0,
          0,
          0,
          0,
          0,
          0,
          0,
          0,
          0,
          0,
          0,
          0,
          0,
          0,
          0,
          0,
          0,
          0,
          0,
          0,
          0,
          0,
          0,
          0,
          0,
          0,
          0,
          0,
          0,
          0,
          0,
          0,
          0,
          0,
          0,
          0,
          0,
          0,
          0,
          0,
          0,
          0,
          0,
          0,
          0,
          0,
          0,
          0,
          0,
          0,
          0,
          0,
          0,
          0,
          0,
          0,
          0,
          0,
          0,
          0,
          0,
          0,
          0,
          0,
          0,
          0,
          0,
          0,
          0,
          0,
          0,
          0,
          0,
          0
        ],
        "scales": [
          0.0015016768593341112,
          0.0017424222314730287,
          0.001994286896660924,
          0.0016349947545677423,
          0.0013022713828831911,
          0.0014216955751180649,
          0.0015362798003479838,
          0.0014898204244673252,
          0.0016940165078267455,
          0.0020404013339430094,
          0.001886840327642858,
          0.0014256850117817521,
          0.0013670395128428936,
          0.0016823727637529373,
          0.0018023396842181683,
          0.001998394727706909,
          0.0018366617150604725,
          0.002009505871683359,
          0.0017978058895096183,
          0.0018529457738623023,
          0.0018362830160185695,
          0.0018157347803935409,
          0.0018175450386479497,
          0.0016512545989826322,
          0.0013769245706498623,
          0.0020809618290513754,
          0.0020576142705976963,
          0.0016935310559347272,
          0.0017446846468374133,
          0.0018450720235705376,
          0.0018568967934697866,
          0.0016300973948091269,
          0.0017012548632919788,
          0.001545243663713336,
          0.0017887093126773834,
          0.0014650451485067606,
          0.0018721085507422686,
          0.0016692643985152245,
          0.0018911062506958842,
          0.001767096808180213,
          0.0016733233351260424,
          0.0021926448680460453,
          0.0017610049108043313,
          0.0017255753045901656,
          0.0017855321057140827,
          0.0016461231280118227,
          0.001619945396669209,
          0.0014528456376865506,
          0.0015523986658081412,
          0.0020853097084909678,
          0.0017580199055373669,
          0.0018892696825787425,
          0.0021107203792780638,
          0.0017769229598343372,
          0.0019474494038149714,
          0.0016589909791946411,
          0.0016471921699121594,
          0.0018455020617693663,
          0.0017750096740201116,
          0.00117961666546762,
          0.001852944609709084,
          0.0016806789208203554,
          0.0018803456332534552,
          0.0018495521508157253,
          0.0017365756211802363,
          0.0018963550683110952,
          0.001513263676315546,
          0.0014012159081175923,
          0.0016981508815661073,
          0.0015723517863079906,
          0.0017622042214497924,
          0.0015673612942919135,
          0.0018925168551504612,
          0.0017079929821193218,
          0.001955699874088168,
          0.0017835281323641539,
          0.0015481894370168447,
          0.0018598265014588833,
          0.0018563823541626334,
          0.0016281805001199245,
          0.0015137644950300455,
          0.0018319623777642846,
          0.002068969653919339,
          0.0017283579800277948,
          0.001619542483240366,
          0.0018175676232203841,
          0.0018404779257252812,
          0.0020166439935564995,
          0.001732157077640295,
          0.0017696110298857093,
          0.001825489685870707,
          0.0018739098450168967,
          0.0019299917621538043,
          0.0016412633704021573,
          0.0019035887671634555,
          0.0015773302875459194,
          0.0012057287385687232,
          0.0018558187875896692,
          0.0017308710375800729,
          0.0013117191847413778,
          0.001930678146891296,
          0.0016463849460706115,
          0.0016189741436392069,
          0.0015656979521736503,
          0.0018883245065808296,
          0.0019115550676360726,
          0.001366970012895763,
          0.0014847870916128159,
          0.0016655490035191178,
          0.0019956419710069895,
          0.0016744796885177493,
          0.0016727828187868,
          0.0021705664694309235,
          0.0016968714771792293,
          0.0018209663685411215,
          0.001669246586970985,
          0.0016438080929219723,
          0.0018951701931655407,
          0.0016307678306475282,
          0.001743494882248342,
          0.00174154550768435,
          0.0015878832200542092,
          0.0018762092804536223,
          0.0016902260249480605,
          0.001526312786154449,
          0.0018441244028508663,
          0.0014432674506679177,
          0.0015727238496765494
        ]
      },
      "is_param": true,
      "mpool_id": 1,
      "name": "gemm_8_weights_array",
      "nbits": 8,
      "offset_start": 135440,
      "qmn": {},
      "shape": [
        128,
        16
      ],
      "shape_map": [
        "CH",
        "CH_IN"
      ],
      "size_bytes": 2048
    },
    {
      "alignment": 4,
      "batch": 0,
      "channel_first": true,
      "channel_last": true,
      "epochs": {
        "end": 1,
        "start": 0
      },
      "flags": "STAI_FLAG_WEIGHTS|STAI_FLAG_CONST|STAI_FLAG_PREALLOCATED",
      "format": "STAI_FORMAT_S32",
      "id": 231,
      "intq": {
        "axis": null,
        "offsets": [],
        "scales": []
      },
      "is_param": true,
      "mpool_id": 1,
      "name": "gemm_9_bias_array",
      "nbits": 32,
      "offset_start": 138512,
      "qmn": {},
      "shape": [
        4
      ],
      "shape_map": [
        "CH"
      ],
      "size_bytes": 16
    },
    {
      "alignment": 4,
      "batch": 0,
      "channel_first": true,
      "channel_last": true,
      "epochs": {
        "end": 37,
        "start": 32
      },
      "flags": "STAI_FLAG_PREALLOCATED|STAI_FLAG_ACTIVATIONS",
      "format": "STAI_FORMAT_S8",
      "id": 186,
      "intq": {
        "axis": 0,
        "offsets": [
          -12
        ],
        "scales": [
          294.45379638671875
        ]
      },
      "is_param": false,
      "mpool_id": 0,
      "name": "gemm_9_output_array",
      "nbits": 8,
      "offset_start": 296,
      "qmn": {},
      "shape": [
        4
      ],
      "shape_map": [
        "CH"
      ],
      "size_bytes": 4
    },
    {
      "alignment": 4,
      "batch": 0,
      "channel_first": false,
      "channel_last": true,
      "epochs": {
        "end": 34,
        "start": 31
      },
      "flags": "STAI_FLAG_PREALLOCATED|STAI_FLAG_ACTIVATIONS|STAI_FLAG_SCRATCHS",
      "format": "STAI_FORMAT_S16",
      "id": 280,
      "intq": {
        "axis": null,
        "offsets": [],
        "scales": []
      },
      "is_param": false,
      "mpool_id": 0,
      "name": "gemm_9_scratch0_array",
      "nbits": 16,
      "offset_start": 0,
      "qmn": {},
      "shape": [
        1,
        1,
        148,
        1
      ],
      "shape_map": [
        "H",
        "W",
        "CH",
        "CH_IN"
      ],
      "size_bytes": 296
    },
    {
      "alignment": 4,
      "batch": 0,
      "channel_first": true,
      "channel_last": true,
      "epochs": {
        "end": 1,
        "start": 0
      },
      "flags": "STAI_FLAG_WEIGHTS|STAI_FLAG_CONST|STAI_FLAG_PREALLOCATED",
      "format": "STAI_FORMAT_S8",
      "id": 228,
      "intq": {
        "axis": 1,
        "offsets": [
          0,
          0,
          0,
          0
        ],
        "scales": [
          0.002058702986687422,
          0.0023035446647554636,
          0.0023035071790218353,
          0.002283677691593766
        ]
      },
      "is_param": true,
      "mpool_id": 1,
      "name": "gemm_9_weights_array",
      "nbits": 8,
      "offset_start": 138000,
      "qmn": {},
      "shape": [
        4,
        128
      ],
      "shape_map": [
        "CH",
        "CH_IN"
      ],
      "size_bytes": 512
    },
    {
      "alignment": 4,
      "batch": 0,
      "channel_first": true,
      "channel_last": true,
      "epochs": {
        "end": 40,
        "start": 36
      },
      "flags": "STAI_FLAG_PREALLOCATED|STAI_FLAG_ACTIVATIONS",
      "format": "STAI_FORMAT_S8",
      "id": 188,
      "intq": {
        "axis": 0,
        "offsets": [
          -128
        ],
        "scales": [
          0.00390625
        ]
      },
      "is_param": false,
      "mpool_id": 0,
      "name": "nl_10_output_array",
      "nbits": 8,
      "offset_start": 4,
      "qmn": {},
      "shape": [
        4
      ],
      "shape_map": [
        "CH"
      ],
      "size_bytes": 4
    },
    {
      "alignment": 4,
      "batch": 0,
      "channel_first": false,
      "channel_last": true,
      "epochs": {
        "end": 38,
        "start": 35
      },
      "flags": "STAI_FLAG_PREALLOCATED|STAI_FLAG_ACTIVATIONS|STAI_FLAG_SCRATCHS",
      "format": "STAI_FORMAT_S32",
      "id": 286,
      "intq": {
        "axis": null,
        "offsets": [],
        "scales": []
      },
      "is_param": false,
      "mpool_id": 0,
      "name": "nl_10_scratch0_array",
      "nbits": 32,
      "offset_start": 0,
      "qmn": {},
      "shape": [
        1,
        1,
        1,
        1
      ],
      "shape_map": [
        "H",
        "W",
        "CH",
        "CH_IN"
      ],
      "size_bytes": 4
    },
    {
      "alignment": 4,
      "batch": 0,
      "channel_first": false,
      "channel_last": true,
      "epochs": {
        "end": 4,
        "start": 2
      },
      "flags": "STAI_FLAG_INPUTS|STAI_FLAG_PREALLOCATED|STAI_FLAG_ACTIVATIONS",
      "format": "STAI_FORMAT_FLOAT",
      "id": 170,
      "intq": {
        "axis": null,
        "offsets": [],
        "scales": []
      },
      "is_param": false,
      "mpool_id": 0,
      "name": "serving_default_input_50_output_array",
      "nbits": 32,
      "offset_start": 11300,
      "qmn": {},
      "shape": [
        32,
        32,
        1
      ],
      "shape_map": [
        "H",
        "W",
        "CH"
      ],
      "size_bytes": 4096
    }
  ],
  "environment": {
    "device": null,
    "generated_model": {
      "generated_time": "2025-01-20T16:43:42+0100",
      "model_files": [
        {
          "name": "word_classifier_data_params.h",
          "signature": "0x94c722981d5c7091d09d1d098b4ae4a7"
        },
        {
          "name": "word_classifier_data_params.c",
          "signature": "0x8c3a64a46c802d0388c1f063d8eaf898"
        },
        {
          "name": "word_classifier_data.h",
          "signature": "0x8aa2617adc0b2345ef72d00319e92114"
        },
        {
          "name": "word_classifier_data.c",
          "signature": "0xf81a837f835d8d6ec69ed78f410a434c"
        },
        {
          "name": "word_classifier_config.h",
          "signature": "0xbb4f4da99f3de51876c06dab20c115d1"
        },
        {
          "name": "word_classifier.h",
          "signature": "0x914d4a40cdaef5f03e7d7c28038126ae"
        },
        {
          "name": "word_classifier.c",
          "signature": "0x30d89598628a606dfce49b0e97c35a9c"
        }
      ],
      "n_params": null,
      "name": "word_classifier",
      "size": null,
      "type": null
    },
    "network_signature": "0x775241cf7b3296e2",
    "test_name": "",
    "tools": [
      {
        "arguments": "generate --target stm32f4 --name word_classifier -m /home/vistek528/TRA_PROJ/NET_prototype/tra_qat_model.tflite --compression none --verbosity 1 --allocate-inputs --allocate-outputs --workspace /tmp/mxAI_workspace100770984849144033032456735041044 --output /home/vistek528/.stm32cubemx/word_classifier_output",
        "environment": [
          "STATS_TYPE=X-CUBE-AI"
        ],
        "input_model": {
          "generated_time": null,
          "model_files": [
            {
              "name": "tra_qat_model.tflite",
              "signature": "0x73e8354ecfe0ee74f0a2f4c71cfc8e7b"
            }
          ],
          "n_params": 137652,
          "name": "tra_qat_model",
          "size": 138528,
          "type": "tflite"
        },
        "name": "ST.EdgeAI.Core",
        "version": "1.0.0-19895"
      }
    ]
  },
  "graphs": [
    {
      "edges": [
        {
          "attributes": null,
          "buffer": 172,
          "edge_kind": 3,
          "end": {
            "node_id": 25,
            "port": 0
          },
          "id": 0,
          "name": "n24-p0_n25-p0",
          "start": {
            "node_id": 24,
            "port": 0
          }
        },
        {
          "attributes": null,
          "buffer": 174,
          "edge_kind": 3,
          "end": {
            "node_id": 26,
            "port": 0
          },
          "id": 1,
          "name": "n25-p0_n26-p0",
          "start": {
            "node_id": 25,
            "port": 0
          }
        },
        {
          "attributes": null,
          "buffer": 176,
          "edge_kind": 3,
          "end": {
            "node_id": 27,
            "port": 0
          },
          "id": 2,
          "name": "n26-p0_n27-p0",
          "start": {
            "node_id": 26,
            "port": 0
          }
        },
        {
          "attributes": null,
          "buffer": 178,
          "edge_kind": 3,
          "end": {
            "node_id": 28,
            "port": 0
          },
          "id": 3,
          "name": "n27-p0_n28-p0",
          "start": {
            "node_id": 27,
            "port": 0
          }
        },
        {
          "attributes": null,
          "buffer": 180,
          "edge_kind": 3,
          "end": {
            "node_id": 29,
            "port": 0
          },
          "id": 4,
          "name": "n28-p0_n29-p0",
          "start": {
            "node_id": 28,
            "port": 0
          }
        },
        {
          "attributes": null,
          "buffer": 182,
          "edge_kind": 3,
          "end": {
            "node_id": 30,
            "port": 0
          },
          "id": 5,
          "name": "n29-p0_n30-p0",
          "start": {
            "node_id": 29,
            "port": 0
          }
        },
        {
          "attributes": null,
          "buffer": 184,
          "edge_kind": 3,
          "end": {
            "node_id": 31,
            "port": 0
          },
          "id": 6,
          "name": "n30-p0_n31-p0",
          "start": {
            "node_id": 30,
            "port": 0
          }
        },
        {
          "attributes": null,
          "buffer": 186,
          "edge_kind": 3,
          "end": {
            "node_id": 32,
            "port": 0
          },
          "id": 7,
          "name": "n31-p0_n32-p0",
          "start": {
            "node_id": 31,
            "port": 0
          }
        },
        {
          "attributes": null,
          "buffer": 188,
          "edge_kind": 3,
          "end": {
            "node_id": 33,
            "port": 0
          },
          "id": 8,
          "name": "n32-p0_n33-p0",
          "start": {
            "node_id": 32,
            "port": 0
          }
        }
      ],
      "exec_time": {
        "counters": [],
        "cycles": null,
        "cycles_by_macc": null,
        "duration_ms": null,
        "percentage": null
      },
      "id": 0,
      "inputs": [
        170
      ],
      "name": "tra_qat_model",
      "nodes": [
        {
          "attributes": {},
          "description": "Conversion",
          "exec_time": {
            "counters": [],
            "cycles": null,
            "cycles_by_macc": null,
            "duration_ms": null,
            "percentage": null
          },
          "id": 24,
          "inputs": [
            170
          ],
          "macc": 2048,
          "mapping": "NODE_SW",
          "name": "conversion_0",
          "original_nodes": [
            "0"
          ],
          "outputs": [
            172
          ],
          "scratchs": [],
          "subgraph_nodes": [],
          "sw_functions": [
            "node_convert"
          ]
        },
        {
          "attributes": {
            "dilation": "{H: 1, W: 1}",
            "filter_size": "(3, 3)",
            "groups": "1",
            "is_depthwise": "False",
            "is_grouped_conv": "False",
            "num_filters": "16",
            "pad": "{H: (0, 0), W: (0, 0)}",
            "stride": "(1, 1)",
            "use_bias": "True",
            "use_deep_kernels": "False"
          },
          "description": "Conv2D",
          "exec_time": {
            "counters": [],
            "cycles": null,
            "cycles_by_macc": null,
            "duration_ms": null,
            "percentage": null
          },
          "id": 25,
          "inputs": [
            172,
            192,
            195
          ],
          "macc": 129616,
          "mapping": "NODE_SW",
          "name": "conv2d_1",
          "original_nodes": [
            "1"
          ],
          "outputs": [
            174
          ],
          "scratchs": [
            237
          ],
          "subgraph_nodes": [],
          "sw_functions": [
            "forward_conv2d_sssa8_ch"
          ]
        },
        {
          "attributes": {
            "dilation": "{H: 1, W: 1}",
            "filter_size": "(3, 3)",
            "groups": "1",
            "is_depthwise": "False",
            "is_grouped_conv": "False",
            "num_filters": "32",
            "pad": "{H: (0, 0), W: (0, 0)}",
            "pool_function": "max",
            "pool_pad": "{H: (0, 0), W: (0, 0)}",
            "pool_size": "(2, 2)",
            "pool_stride": "(2, 2)",
            "stride": "(1, 1)",
            "use_bias": "True",
            "use_deep_kernels": "True"
          },
          "description": "Conv2D",
          "exec_time": {
            "counters": [],
            "cycles": null,
            "cycles_by_macc": null,
            "duration_ms": null,
            "percentage": null
          },
          "id": 26,
          "inputs": [
            174,
            198,
            201
          ],
          "macc": 3637792,
          "mapping": "NODE_SW",
          "name": "conv2d_2",
          "original_nodes": [
            "3"
          ],
          "outputs": [
            176
          ],
          "scratchs": [
            246,
            250
          ],
          "subgraph_nodes": [],
          "sw_functions": [
            " forward_conv2d_deep_3x3_sssa8_ch_nl_pool"
          ]
        },
        {
          "attributes": {
            "dilation": "{H: 1, W: 1}",
            "filter_size": "(3, 3)",
            "groups": "1",
            "is_depthwise": "False",
            "is_grouped_conv": "False",
            "num_filters": "32",
            "pad": "{H: (0, 0), W: (0, 0)}",
            "stride": "(1, 1)",
            "use_bias": "True",
            "use_deep_kernels": "True"
          },
          "description": "Conv2D",
          "exec_time": {
            "counters": [],
            "cycles": null,
            "cycles_by_macc": null,
            "duration_ms": null,
            "percentage": null
          },
          "id": 27,
          "inputs": [
            176,
            204,
            207
          ],
          "macc": 1327136,
          "mapping": "NODE_SW",
          "name": "conv2d_4",
          "original_nodes": [
            "4"
          ],
          "outputs": [
            178
          ],
          "scratchs": [
            256
          ],
          "subgraph_nodes": [],
          "sw_functions": [
            "forward_conv2d_deep_3x3_sssa8_ch"
          ]
        },
        {
          "attributes": {
            "dilation": "{H: 1, W: 1}",
            "filter_size": "(3, 3)",
            "groups": "1",
            "is_depthwise": "False",
            "is_grouped_conv": "False",
            "num_filters": "64",
            "pad": "{H: (0, 0), W: (0, 0)}",
            "stride": "(1, 1)",
            "use_bias": "True",
            "use_deep_kernels": "True"
          },
          "description": "Conv2D",
          "exec_time": {
            "counters": [],
            "cycles": null,
            "cycles_by_macc": null,
            "duration_ms": null,
            "percentage": null
          },
          "id": 28,
          "inputs": [
            178,
            210,
            213
          ],
          "macc": 1843264,
          "mapping": "NODE_SW",
          "name": "conv2d_5",
          "original_nodes": [
            "5"
          ],
          "outputs": [
            180
          ],
          "scratchs": [
            262
          ],
          "subgraph_nodes": [],
          "sw_functions": [
            "forward_conv2d_deep_3x3_sssa8_ch"
          ]
        },
        {
          "attributes": {
            "num_units": "16",
            "use_bias": "True"
          },
          "description": "Dense",
          "exec_time": {
            "counters": [],
            "cycles": null,
            "cycles_by_macc": null,
            "duration_ms": null,
            "percentage": null
          },
          "id": 29,
          "inputs": [
            180,
            216,
            219
          ],
          "macc": 102416,
          "mapping": "NODE_SW",
          "name": "gemm_7",
          "original_nodes": [
            "7"
          ],
          "outputs": [
            182
          ],
          "scratchs": [
            268
          ],
          "subgraph_nodes": [],
          "sw_functions": [
            "forward_dense_integer_SSSA_ch"
          ]
        },
        {
          "attributes": {
            "num_units": "128",
            "use_bias": "True"
          },
          "description": "Dense",
          "exec_time": {
            "counters": [],
            "cycles": null,
            "cycles_by_macc": null,
            "duration_ms": null,
            "percentage": null
          },
          "id": 30,
          "inputs": [
            182,
            222,
            225
          ],
          "macc": 2176,
          "mapping": "NODE_SW",
          "name": "gemm_8",
          "original_nodes": [
            "8"
          ],
          "outputs": [
            184
          ],
          "scratchs": [
            274
          ],
          "subgraph_nodes": [],
          "sw_functions": [
            "forward_dense_integer_SSSA_ch"
          ]
        },
        {
          "attributes": {
            "num_units": "4",
            "use_bias": "True"
          },
          "description": "Dense",
          "exec_time": {
            "counters": [],
            "cycles": null,
            "cycles_by_macc": null,
            "duration_ms": null,
            "percentage": null
          },
          "id": 31,
          "inputs": [
            184,
            228,
            231
          ],
          "macc": 516,
          "mapping": "NODE_SW",
          "name": "gemm_9",
          "original_nodes": [
            "9"
          ],
          "outputs": [
            186
          ],
          "scratchs": [
            280
          ],
          "subgraph_nodes": [],
          "sw_functions": [
            "forward_dense_integer_SSSA_ch"
          ]
        },
        {
          "attributes": {
            "axis": "CH",
            "nonlinearity": "softmax",
            "orig_axis": "-1",
            "param_fmt": "(SIGNED, 32 bit, C Size: 32 bits)",
            "params": "[2147483647, 30, -1]"
          },
          "description": "Nonlinearity",
          "exec_time": {
            "counters": [],
            "cycles": null,
            "cycles_by_macc": null,
            "duration_ms": null,
            "percentage": null
          },
          "id": 32,
          "inputs": [
            186
          ],
          "macc": 60,
          "mapping": "NODE_SW",
          "name": "nl_10",
          "original_nodes": [
            "10"
          ],
          "outputs": [
            188
          ],
          "scratchs": [
            286
          ],
          "subgraph_nodes": [],
          "sw_functions": [
            "forward_sm_integer"
          ]
        },
        {
          "attributes": {},
          "description": "Conversion",
          "exec_time": {
            "counters": [],
            "cycles": null,
            "cycles_by_macc": null,
            "duration_ms": null,
            "percentage": null
          },
          "id": 33,
          "inputs": [
            188
          ],
          "macc": 8,
          "mapping": "NODE_SW",
          "name": "conversion_11",
          "original_nodes": [
            "11"
          ],
          "outputs": [
            190
          ],
          "scratchs": [],
          "subgraph_nodes": [],
          "sw_functions": [
            "node_convert"
          ]
        }
      ],
      "original_inputs": [
        {
          "serving_default_input_50": {
            "data_type": "float32",
            "shape": "(BATCH: 1, H: 32, W: 32, CH: 1)"
          }
        }
      ],
      "original_outputs": [
        {
          "conversion_11": {
            "data_type": "float32",
            "shape": "(BATCH: 1, CH: 4)"
          }
        }
      ],
      "outputs": [
        190
      ]
    }
  ],
  "json_schema_version": "2.0",
  "memory_accesses": [],
  "memory_footprint": {
    "activations": 22784,
    "io": [
      0,
      0
    ],
    "kernel_flash": 36882,
    "kernel_ram": 4313,
    "series": "stm32f4",
    "toolchain": "arm-none-eabi-gcc (15:10.3-2021.07-4) 10.3.1 20210621 (release)",
    "toolchain_flash": 2334,
    "toolchain_ram": 1,
    "weights": 138528
  },
  "memory_pools": [
    {
      "address": "NULL",
      "alignment": 4,
      "attributes": {
        "latency": "HIGH",
        "score": 768,
        "throughput": "LOW"
      },
      "buffers": [
        170,
        172,
        174,
        176,
        178,
        180,
        182,
        184,
        186,
        188,
        190,
        237,
        246,
        250,
        256,
        262,
        268,
        274,
        280,
        286
      ],
      "cacheable": null,
      "id": 0,
      "name": "heap_overlay_pool",
      "offset_start": 0,
      "persistent": false,
      "pipelined": null,
      "rights": "ACC_WRITE",
      "size_bytes": -1,
      "subpools": [],
      "used_size_bytes": 22784,
      "user_allocated": false,
      "virtual": false
    },
    {
      "address": "NULL",
      "alignment": 0,
      "attributes": {
        "latency": "UNDEF",
        "score": 0,
        "throughput": "UNDEF"
      },
      "buffers": [
        192,
        195,
        198,
        201,
        204,
        207,
        210,
        213,
        216,
        219,
        222,
        225,
        228,
        231
      ],
      "cacheable": null,
      "id": 1,
      "name": "weights_array",
      "offset_start": 0,
      "persistent": true,
      "pipelined": null,
      "rights": "ACC_READ",
      "size_bytes": -1,
      "subpools": [],
      "used_size_bytes": 138528,
      "user_allocated": false,
      "virtual": false
    }
  ],
  "power_estimates": [],
  "validation": {
    "val_error": null,
    "val_error_desc": null,
    "val_metrics": []
  }
}